photosort/__init__.py
photosort/config.py
photosort/exceptions.py
photosort/exif.py
photosort/media.py
photosort/photodb.py
photosort/photosort.py
photosort/walk.py
photosort/test/__init__.py
photosort/test/test.py
photosort/test/data/.gitkeep
photosort/test/data/media1/img1.jpg
photosort/test/data/media1/img1_dup.jpg
photosort/test/data/media2/BigBuckBunny.avi
photosort/test/data/media2/mov1.mp4
photosort/test/data/media2/mov1_dup.mp4
photosort/test/data/media2/mov_exif.m4v
photosort/test/testcases/__init__.py
photosort/test/testcases/test_001_walk_for_media.py
photosort/test/testcases/test_002_exif_media.py
photosort/test/testcases/test_003_noexif_media.py
photosort-2024.1.0.dist-info/METADATA
photosort-2024.1.0.dist-info/WHEEL
photosort-2024.1.0.dist-info/entry_points.txt
photosort-2024.1.0.dist-info/RECORD
