Metadata-Version: 2.3
Name: photosort
Version: 2024.1.0
Summary: Picture inbox simplified
Author-email: Miguel Angel Ajo Pelayo <miguelangel@ajo.es>
Requires-Python: >=3.9
Requires-Dist: pyaml>=24.7.0
Requires-Dist: pyexiftool>=0.5.6
